Fiasko_Bro-0.0.1.1.dist-info/DESCRIPTION.rst
Fiasko_Bro-0.0.1.1.dist-info/METADATA
Fiasko_Bro-0.0.1.1.dist-info/RECORD
Fiasko_Bro-0.0.1.1.dist-info/WHEEL
Fiasko_Bro-0.0.1.1.dist-info/metadata.json
Fiasko_Bro-0.0.1.1.dist-info/top_level.txt
fiasko_bro/__init__.py
fiasko_bro/ast_helpers.py
fiasko_bro/ast_nodes_validators.py
fiasko_bro/code_helpers.py
fiasko_bro/code_validator.py
fiasko_bro/config.py
fiasko_bro/file_helpers.py
fiasko_bro/i18n.py
fiasko_bro/list_helpers.py
fiasko_bro/repository_info.py
fiasko_bro/url_helpers.py
fiasko_bro/validator_helpers.py
fiasko_bro/locale/ru_RU/LC_MESSAGES/fiasko_bro.mo
fiasko_bro/locale/ru_RU/LC_MESSAGES/fiasko_bro.po
fiasko_bro/validators/__init__.py
fiasko_bro/validators/code_inclusion.py
fiasko_bro/validators/comments.py
fiasko_bro/validators/commits.py
fiasko_bro/validators/encoding.py
fiasko_bro/validators/files.py
fiasko_bro/validators/imports.py
fiasko_bro/validators/naming.py
fiasko_bro/validators/other_languages.py
fiasko_bro/validators/pythonic.py
fiasko_bro/validators/readme.py
fiasko_bro/validators/requirements.py
fiasko_bro/validators/syntax.py
